MANIFEST.in
README.md
requirements.txt
setup.cfg
setup.py
tests/test_base.py
tests/test_remote.py
tests/test_utils.py
xunleipy/__init__.py
xunleipy/base.py
xunleipy/fp.py
xunleipy/remote.py
xunleipy/rk.py
xunleipy/rsa_lib.py
xunleipy/utils.py
xunleipy/vod.py
xunleipy.egg-info/PKG-INFO
xunleipy.egg-info/SOURCES.txt
xunleipy.egg-info/dependency_links.txt
xunleipy.egg-info/requires.txt
xunleipy.egg-info/top_level.txt